{
    "AssemblyPath": "setting\\HealthCare.Data.Employee.dll",
    "IsLocked": false,
    "IsSelected": false,
    "IsTestPassed": true,
    "ObjectFullName": "HealthCare.Data.Employee",
    "ObjectName": "Employee",
    "SelectedSource": {
        "IsEffect": false,
        "ResourceAddress": "select * FROM dbo.[comm.sfra_employee]",
        "SourceEnum": 0
    },
    "TargetMemberDetails": [
        {
            "ChildTargetMemberDetails": [],
            "ErrorMsg": null,
            "Expression": "#UniqueID",
            "ExpressionValue": "OYAM1198",
            "ExpressionValueType": "String",
            "FullPropertyName": "Employee.UniqueId",
            "IsErrorExpression": false,
            "SelectedSubType": null
        },
        {
            "ChildTargetMemberDetails": [],
            "ErrorMsg": null,
            "Expression": "#DisplayName.ToString().Trim()",
            "ExpressionValue": "欧阳爱梅",
            "ExpressionValueType": "String",
            "FullPropertyName": "Employee.DisplayName",
            "IsErrorExpression": false,
            "SelectedSubType": null
        },
        {
            "ChildTargetMemberDetails": [],
            "ErrorMsg": null,
            "Expression": "#UniqueID",
            "ExpressionValue": "OYAM1198",
            "ExpressionValueType": "String",
            "FullPropertyName": "Employee.Code",
            "IsErrorExpression": false,
            "SelectedSubType": null
        },
        {
            "ChildTargetMemberDetails": [],
            "ErrorMsg": null,
            "Expression": null,
            "ExpressionValue": -1,
            "ExpressionValueType": "Int32",
            "FullPropertyName": "Employee.DisplayOrder",
            "IsErrorExpression": null,
            "SelectedSubType": null
        },
        {
            "ChildTargetMemberDetails": [],
            "ErrorMsg": null,
            "Expression": null,
            "ExpressionValue": null,
            "ExpressionValueType": null,
            "FullPropertyName": "Employee.IsDisabled",
            "IsErrorExpression": null,
            "SelectedSubType": null
        },
        {
            "ChildTargetMemberDetails": [],
            "ErrorMsg": null,
            "Expression": "#Departmentid",
            "ExpressionValue": "307201",
            "ExpressionValueType": "String",
            "FullPropertyName": "Employee.DepartmentId",
            "IsErrorExpression": false,
            "SelectedSubType": null
        },
        {
            "ChildTargetMemberDetails": [],
            "ErrorMsg": null,
            "Expression": "#JobNO.ToString().Trim()",
            "ExpressionValue": "1198",
            "ExpressionValueType": "String",
            "FullPropertyName": "Employee.JobNo",
            "IsErrorExpression": false,
            "SelectedSubType": null
        },
        {
            "ChildTargetMemberDetails": [],
            "ErrorMsg": null,
            "Expression": "#JobTitle.ToString().Trim()",
            "ExpressionValue": "主治医师",
            "ExpressionValueType": "String",
            "FullPropertyName": "Employee.JobTitle",
            "IsErrorExpression": false,
            "SelectedSubType": null
        },
        {
            "ChildTargetMemberDetails": [],
            "ErrorMsg": null,
            "Expression": null,
            "ExpressionValue": null,
            "ExpressionValueType": null,
            "FullPropertyName": "Employee.Signature",
            "IsErrorExpression": null,
            "SelectedSubType": null
        },
        {
            "ChildTargetMemberDetails": [],
            "ErrorMsg": null,
            "Expression": null,
            "ExpressionValue": null,
            "ExpressionValueType": null,
            "FullPropertyName": "Employee.Age",
            "IsErrorExpression": null,
            "SelectedSubType": null
        },
        {
            "ChildTargetMemberDetails": [],
            "ErrorMsg": null,
            "Expression": null,
            "ExpressionValue": null,
            "ExpressionValueType": null,
            "FullPropertyName": "Employee.Birthday",
            "IsErrorExpression": null,
            "SelectedSubType": null
        },
        {
            "ChildTargetMemberDetails": [],
            "ErrorMsg": null,
            "Expression": null,
            "ExpressionValue": null,
            "ExpressionValueType": null,
            "FullPropertyName": "Employee.Gender",
            "IsErrorExpression": null,
            "SelectedSubType": null
        }
    ],
    "IsSyncing": false
}